quetz_client/__init__.py
quetz_client/_version.py
quetz_client/cli.py
quetz_client/client.py
quetz_client-0.5.0.dist-info/LICENSE
quetz_client-0.5.0.dist-info/METADATA
quetz_client-0.5.0.dist-info/WHEEL
quetz_client-0.5.0.dist-info/entry_points.txt
quetz_client-0.5.0.dist-info/top_level.txt
quetz_client-0.5.0.dist-info/RECORD
