Metadata-Version: 2.1
Name: quetz-client
Version: 0.5.0
Summary: A Python client to interact with a Quetz server.
Home-page: https://github.com/mamba-org/quetz-client
Author: QuantCo, Inc.
Author-email: noreply@quantco.com
Classifier: Programming Language :: Python :: 3
Classifier: Programming Language :: Python :: 3.8
Classifier: Programming Language :: Python :: 3.9
Classifier: Programming Language :: Python :: 3.10
Requires-Python: >=3.8
License-File: LICENSE
Requires-Dist: fire
Requires-Dist: requests
Requires-Dist: dacite
